{
  "date": "2026-04-28",
  "generated_at": "2026-04-28T08:25:42.565882",
  "hits_qualifiers": [
    {
      "player": "Jake Fraley (TB)",
      "over_0.5_H": 80.0,
      "over_1.5_H": 0.0,
      "over_0.5_K": 70.0,
      "over_1.5_K": 30.0,
      "over_1.5_HRR": 40.0,
      "games_considered": 10,
      "player_id": 641584
    },
    {
      "player": "Junior Caminero (TB)",
      "over_0.5_H": 90.0,
      "over_1.5_H": 30.0,
      "over_0.5_K": 30.0,
      "over_1.5_K": 10.0,
      "over_1.5_HRR": 60.0,
      "games_considered": 10,
      "player_id": 691406
    },
    {
      "player": "Brayan Rocchio (CLE)",
      "over_0.5_H": 80.0,
      "over_1.5_H": 30.0,
      "over_0.5_K": 30.0,
      "over_1.5_K": 0.0,
      "over_1.5_HRR": 80.0,
      "games_considered": 10,
      "player_id": 677587
    },
    {
      "player": "Daniel Schneemann (CLE)",
      "over_0.5_H": 80.0,
      "over_1.5_H": 30.0,
      "over_0.5_K": 80.0,
      "over_1.5_K": 40.0,
      "over_1.5_HRR": 60.0,
      "games_considered": 10,
      "player_id": 682177
    },
    {
      "player": "Yordan Alvarez (HOU)",
      "over_0.5_H": 100.0,
      "over_1.5_H": 60.0,
      "over_0.5_K": 20.0,
      "over_1.5_K": 0.0,
      "over_1.5_HRR": 80.0,
      "games_considered": 10,
      "player_id": 670541
    },
    {
      "player": "Hunter Goodman (COL)",
      "over_0.5_H": 80.0,
      "over_1.5_H": 30.0,
      "over_0.5_K": 100.0,
      "over_1.5_K": 50.0,
      "over_1.5_HRR": 70.0,
      "games_considered": 10,
      "player_id": 696100
    },
    {
      "player": "Mickey Moniak (COL)",
      "over_0.5_H": 100.0,
      "over_1.5_H": 30.0,
      "over_0.5_K": 80.0,
      "over_1.5_K": 10.0,
      "over_1.5_HRR": 50.0,
      "games_considered": 10,
      "player_id": 666160
    },
    {
      "player": "Troy Johnston (COL)",
      "over_0.5_H": 80.0,
      "over_1.5_H": 30.0,
      "over_0.5_K": 60.0,
      "over_1.5_K": 30.0,
      "over_1.5_HRR": 70.0,
      "games_considered": 10,
      "player_id": 687859
    },
    {
      "player": "Elly De La Cruz (CIN)",
      "over_0.5_H": 80.0,
      "over_1.5_H": 20.0,
      "over_0.5_K": 60.0,
      "over_1.5_K": 40.0,
      "over_1.5_HRR": 70.0,
      "games_considered": 10,
      "player_id": 682829
    },
    {
      "player": "Iván Herrera (STL)",
      "over_0.5_H": 90.0,
      "over_1.5_H": 20.0,
      "over_0.5_K": 60.0,
      "over_1.5_K": 30.0,
      "over_1.5_HRR": 60.0,
      "games_considered": 10,
      "player_id": 671056
    },
    {
      "player": "JJ Wetherholt (STL)",
      "over_0.5_H": 80.0,
      "over_1.5_H": 10.0,
      "over_0.5_K": 50.0,
      "over_1.5_K": 40.0,
      "over_1.5_HRR": 70.0,
      "games_considered": 10,
      "player_id": 802139
    },
    {
      "player": "Masyn Winn (STL)",
      "over_0.5_H": 80.0,
      "over_1.5_H": 50.0,
      "over_0.5_K": 70.0,
      "over_1.5_K": 30.0,
      "over_1.5_HRR": 80.0,
      "games_considered": 10,
      "player_id": 691026
    },
    {
      "player": "Nathan Church (STL)",
      "over_0.5_H": 80.0,
      "over_1.5_H": 40.0,
      "over_0.5_K": 50.0,
      "over_1.5_K": 30.0,
      "over_1.5_HRR": 40.0,
      "games_considered": 10,
      "player_id": 701675
    },
    {
      "player": "Pedro Pagés (STL)",
      "over_0.5_H": 80.0,
      "over_1.5_H": 10.0,
      "over_0.5_K": 40.0,
      "over_1.5_K": 10.0,
      "over_1.5_HRR": 60.0,
      "games_considered": 10,
      "player_id": 686780
    },
    {
      "player": "Nick Gonzales (PIT)",
      "over_0.5_H": 80.0,
      "over_1.5_H": 50.0,
      "over_0.5_K": 50.0,
      "over_1.5_K": 20.0,
      "over_1.5_HRR": 70.0,
      "games_considered": 10,
      "player_id": 693304
    },
    {
      "player": "Jung Hoo Lee (SF)",
      "over_0.5_H": 80.0,
      "over_1.5_H": 60.0,
      "over_0.5_K": 40.0,
      "over_1.5_K": 0.0,
      "over_1.5_HRR": 80.0,
      "games_considered": 10,
      "player_id": 808982
    },
    {
      "player": "Bryson Stott (PHI)",
      "over_0.5_H": 80.0,
      "over_1.5_H": 10.0,
      "over_0.5_K": 50.0,
      "over_1.5_K": 0.0,
      "over_1.5_HRR": 40.0,
      "games_considered": 10,
      "player_id": 681082
    },
    {
      "player": "Wilyer Abreu (BOS)",
      "over_0.5_H": 80.0,
      "over_1.5_H": 30.0,
      "over_0.5_K": 30.0,
      "over_1.5_K": 0.0,
      "over_1.5_HRR": 60.0,
      "games_considered": 10,
      "player_id": 677800
    },
    {
      "player": "Ernie Clement (TOR)",
      "over_0.5_H": 90.0,
      "over_1.5_H": 50.0,
      "over_0.5_K": 50.0,
      "over_1.5_K": 0.0,
      "over_1.5_HRR": 70.0,
      "games_considered": 10,
      "player_id": 676391
    },
    {
      "player": "Jesús Sánchez (TOR)",
      "over_0.5_H": 80.0,
      "over_1.5_H": 0.0,
      "over_0.5_K": 50.0,
      "over_1.5_K": 20.0,
      "over_1.5_HRR": 40.0,
      "games_considered": 10,
      "player_id": 660821
    },
    {
      "player": "Brady House (WSH)",
      "over_0.5_H": 80.0,
      "over_1.5_H": 0.0,
      "over_0.5_K": 100.0,
      "over_1.5_K": 40.0,
      "over_1.5_HRR": 50.0,
      "games_considered": 10,
      "player_id": 691781
    },
    {
      "player": "Bo Bichette (NYM)",
      "over_0.5_H": 80.0,
      "over_1.5_H": 10.0,
      "over_0.5_K": 60.0,
      "over_1.5_K": 10.0,
      "over_1.5_HRR": 50.0,
      "games_considered": 10,
      "player_id": 666182
    },
    {
      "player": "Juan Soto (NYM)",
      "over_0.5_H": 80.0,
      "over_1.5_H": 10.0,
      "over_0.5_K": 50.0,
      "over_1.5_K": 0.0,
      "over_1.5_HRR": 40.0,
      "games_considered": 10,
      "player_id": 665742
    },
    {
      "player": "Kevin McGonigle (DET)",
      "over_0.5_H": 100.0,
      "over_1.5_H": 40.0,
      "over_0.5_K": 50.0,
      "over_1.5_K": 0.0,
      "over_1.5_HRR": 90.0,
      "games_considered": 10,
      "player_id": 805808
    },
    {
      "player": "Riley Greene (DET)",
      "over_0.5_H": 80.0,
      "over_1.5_H": 50.0,
      "over_0.5_K": 60.0,
      "over_1.5_K": 30.0,
      "over_1.5_HRR": 70.0,
      "games_considered": 10,
      "player_id": 682985
    },
    {
      "player": "Dominic Smith (ATL)",
      "over_0.5_H": 90.0,
      "over_1.5_H": 20.0,
      "over_0.5_K": 30.0,
      "over_1.5_K": 10.0,
      "over_1.5_HRR": 70.0,
      "games_considered": 10,
      "player_id": 642086
    },
    {
      "player": "Drake Baldwin (ATL)",
      "over_0.5_H": 80.0,
      "over_1.5_H": 40.0,
      "over_0.5_K": 70.0,
      "over_1.5_K": 30.0,
      "over_1.5_HRR": 80.0,
      "games_considered": 10,
      "player_id": 686948
    },
    {
      "player": "Matt Olson (ATL)",
      "over_0.5_H": 80.0,
      "over_1.5_H": 30.0,
      "over_0.5_K": 50.0,
      "over_1.5_K": 20.0,
      "over_1.5_HRR": 90.0,
      "games_considered": 10,
      "player_id": 621566
    },
    {
      "player": "Michael Harris II (ATL)",
      "over_0.5_H": 80.0,
      "over_1.5_H": 50.0,
      "over_0.5_K": 10.0,
      "over_1.5_K": 10.0,
      "over_1.5_HRR": 80.0,
      "games_considered": 10,
      "player_id": 671739
    },
    {
      "player": "Ozzie Albies (ATL)",
      "over_0.5_H": 90.0,
      "over_1.5_H": 40.0,
      "over_0.5_K": 20.0,
      "over_1.5_K": 0.0,
      "over_1.5_HRR": 70.0,
      "games_considered": 10,
      "player_id": 645277
    },
    {
      "player": "Cole Young (SEA)",
      "over_0.5_H": 80.0,
      "over_1.5_H": 30.0,
      "over_0.5_K": 70.0,
      "over_1.5_K": 0.0,
      "over_1.5_HRR": 50.0,
      "games_considered": 10,
      "player_id": 702284
    },
    {
      "player": "Julio Rodríguez (SEA)",
      "over_0.5_H": 80.0,
      "over_1.5_H": 40.0,
      "over_0.5_K": 60.0,
      "over_1.5_K": 10.0,
      "over_1.5_HRR": 60.0,
      "games_considered": 10,
      "player_id": 677594
    },
    {
      "player": "Byron Buxton (MIN)",
      "over_0.5_H": 80.0,
      "over_1.5_H": 10.0,
      "over_0.5_K": 90.0,
      "over_1.5_K": 50.0,
      "over_1.5_HRR": 50.0,
      "games_considered": 10,
      "player_id": 621439
    },
    {
      "player": "Jorge Soler (LAA)",
      "over_0.5_H": 80.0,
      "over_1.5_H": 20.0,
      "over_0.5_K": 80.0,
      "over_1.5_K": 40.0,
      "over_1.5_HRR": 50.0,
      "games_considered": 10,
      "player_id": 624585
    },
    {
      "player": "Chase Meidroth (CWS)",
      "over_0.5_H": 90.0,
      "over_1.5_H": 40.0,
      "over_0.5_K": 70.0,
      "over_1.5_K": 20.0,
      "over_1.5_HRR": 70.0,
      "games_considered": 10,
      "player_id": 805367
    },
    {
      "player": "Colson Montgomery (CWS)",
      "over_0.5_H": 80.0,
      "over_1.5_H": 30.0,
      "over_0.5_K": 80.0,
      "over_1.5_K": 40.0,
      "over_1.5_HRR": 80.0,
      "games_considered": 10,
      "player_id": 695657
    },
    {
      "player": "Miguel Vargas (CWS)",
      "over_0.5_H": 80.0,
      "over_1.5_H": 30.0,
      "over_0.5_K": 50.0,
      "over_1.5_K": 10.0,
      "over_1.5_HRR": 80.0,
      "games_considered": 10,
      "player_id": 678246
    },
    {
      "player": "Munetaka Murakami (CWS)",
      "over_0.5_H": 80.0,
      "over_1.5_H": 40.0,
      "over_0.5_K": 80.0,
      "over_1.5_K": 50.0,
      "over_1.5_HRR": 70.0,
      "games_considered": 10,
      "player_id": 808959
    },
    {
      "player": "Alek Thomas (AZ)",
      "over_0.5_H": 80.0,
      "over_1.5_H": 30.0,
      "over_0.5_K": 40.0,
      "over_1.5_K": 20.0,
      "over_1.5_HRR": 50.0,
      "games_considered": 10,
      "player_id": 677950
    },
    {
      "player": "Ildemaro Vargas (AZ)",
      "over_0.5_H": 100.0,
      "over_1.5_H": 30.0,
      "over_0.5_K": 40.0,
      "over_1.5_K": 10.0,
      "over_1.5_HRR": 70.0,
      "games_considered": 10,
      "player_id": 545121
    },
    {
      "player": "Jose Fernandez (AZ)",
      "over_0.5_H": 90.0,
      "over_1.5_H": 40.0,
      "over_0.5_K": 70.0,
      "over_1.5_K": 10.0,
      "over_1.5_HRR": 80.0,
      "games_considered": 10,
      "player_id": 699912
    },
    {
      "player": "Ketel Marte (AZ)",
      "over_0.5_H": 90.0,
      "over_1.5_H": 40.0,
      "over_0.5_K": 50.0,
      "over_1.5_K": 10.0,
      "over_1.5_HRR": 70.0,
      "games_considered": 10,
      "player_id": 606466
    },
    {
      "player": "Brandon Lockridge (MIL)",
      "over_0.5_H": 80.0,
      "over_1.5_H": 10.0,
      "over_0.5_K": 80.0,
      "over_1.5_K": 40.0,
      "over_1.5_HRR": 40.0,
      "games_considered": 10,
      "player_id": 663604
    },
    {
      "player": "José Caballero (NYY)",
      "over_0.5_H": 80.0,
      "over_1.5_H": 40.0,
      "over_0.5_K": 50.0,
      "over_1.5_K": 10.0,
      "over_1.5_HRR": 40.0,
      "games_considered": 10,
      "player_id": 676609
    },
    {
      "player": "Josh Jung (TEX)",
      "over_0.5_H": 90.0,
      "over_1.5_H": 40.0,
      "over_0.5_K": 40.0,
      "over_1.5_K": 10.0,
      "over_1.5_HRR": 80.0,
      "games_considered": 10,
      "player_id": 673962
    },
    {
      "player": "Bobby Witt Jr. (KC)",
      "over_0.5_H": 90.0,
      "over_1.5_H": 50.0,
      "over_0.5_K": 60.0,
      "over_1.5_K": 10.0,
      "over_1.5_HRR": 70.0,
      "games_considered": 10,
      "player_id": 677951
    },
    {
      "player": "Jac Caglianone (KC)",
      "over_0.5_H": 90.0,
      "over_1.5_H": 10.0,
      "over_0.5_K": 70.0,
      "over_1.5_K": 30.0,
      "over_1.5_HRR": 70.0,
      "games_considered": 10,
      "player_id": 695506
    },
    {
      "player": "Carlos Cortes (ATH)",
      "over_0.5_H": 80.0,
      "over_1.5_H": 50.0,
      "over_0.5_K": 20.0,
      "over_1.5_K": 0.0,
      "over_1.5_HRR": 50.0,
      "games_considered": 10,
      "player_id": 666126
    },
    {
      "player": "Jacob Wilson (ATH)",
      "over_0.5_H": 80.0,
      "over_1.5_H": 60.0,
      "over_0.5_K": 30.0,
      "over_1.5_K": 0.0,
      "over_1.5_HRR": 60.0,
      "games_considered": 10,
      "player_id": 805779
    },
    {
      "player": "Nick Kurtz (ATH)",
      "over_0.5_H": 80.0,
      "over_1.5_H": 40.0,
      "over_0.5_K": 70.0,
      "over_1.5_K": 30.0,
      "over_1.5_HRR": 70.0,
      "games_considered": 10,
      "player_id": 701762
    },
    {
      "player": "Shea Langeliers (ATH)",
      "over_0.5_H": 80.0,
      "over_1.5_H": 50.0,
      "over_0.5_K": 60.0,
      "over_1.5_K": 20.0,
      "over_1.5_HRR": 80.0,
      "games_considered": 10,
      "player_id": 669127
    },
    {
      "player": "Carson Kelly (CHC)",
      "over_0.5_H": 80.0,
      "over_1.5_H": 30.0,
      "over_0.5_K": 40.0,
      "over_1.5_K": 20.0,
      "over_1.5_HRR": 60.0,
      "games_considered": 10,
      "player_id": 608348
    },
    {
      "player": "Ian Happ (CHC)",
      "over_0.5_H": 80.0,
      "over_1.5_H": 20.0,
      "over_0.5_K": 70.0,
      "over_1.5_K": 30.0,
      "over_1.5_HRR": 70.0,
      "games_considered": 10,
      "player_id": 664023
    },
    {
      "player": "Michael Busch (CHC)",
      "over_0.5_H": 80.0,
      "over_1.5_H": 30.0,
      "over_0.5_K": 90.0,
      "over_1.5_K": 30.0,
      "over_1.5_HRR": 60.0,
      "games_considered": 10,
      "player_id": 683737
    },
    {
      "player": "Moisés Ballesteros (CHC)",
      "over_0.5_H": 80.0,
      "over_1.5_H": 30.0,
      "over_0.5_K": 20.0,
      "over_1.5_K": 10.0,
      "over_1.5_HRR": 70.0,
      "games_considered": 10,
      "player_id": 694208
    },
    {
      "player": "Fernando Tatis Jr. (SD)",
      "over_0.5_H": 80.0,
      "over_1.5_H": 30.0,
      "over_0.5_K": 80.0,
      "over_1.5_K": 30.0,
      "over_1.5_HRR": 60.0,
      "games_considered": 10,
      "player_id": 665487
    },
    {
      "player": "Luis Campusano (SD)",
      "over_0.5_H": 80.0,
      "over_1.5_H": 30.0,
      "over_0.5_K": 30.0,
      "over_1.5_K": 10.0,
      "over_1.5_HRR": 70.0,
      "games_considered": 10,
      "player_id": 669134
    },
    {
      "player": "Liam Hicks (MIA)",
      "over_0.5_H": 80.0,
      "over_1.5_H": 30.0,
      "over_0.5_K": 20.0,
      "over_1.5_K": 10.0,
      "over_1.5_HRR": 60.0,
      "games_considered": 10,
      "player_id": 689414
    },
    {
      "player": "Otto Lopez (MIA)",
      "over_0.5_H": 80.0,
      "over_1.5_H": 20.0,
      "over_0.5_K": 60.0,
      "over_1.5_K": 30.0,
      "over_1.5_HRR": 70.0,
      "games_considered": 10,
      "player_id": 672640
    },
    {
      "player": "Max Muncy (LAD)",
      "over_0.5_H": 80.0,
      "over_1.5_H": 30.0,
      "over_0.5_K": 40.0,
      "over_1.5_K": 10.0,
      "over_1.5_HRR": 60.0,
      "games_considered": 10,
      "player_id": 571970
    }
  ],
  "strikeouts_qualifiers": [
    {
      "player": "Jonathan Aranda (TB)",
      "over_0.5_H": 60.0,
      "over_1.5_H": 20.0,
      "over_0.5_K": 90.0,
      "over_1.5_K": 20.0,
      "over_1.5_HRR": 50.0,
      "games_considered": 10,
      "player_id": 666018
    },
    {
      "player": "Daniel Schneemann (CLE)",
      "over_0.5_H": 80.0,
      "over_1.5_H": 30.0,
      "over_0.5_K": 80.0,
      "over_1.5_K": 40.0,
      "over_1.5_HRR": 60.0,
      "games_considered": 10,
      "player_id": 682177
    },
    {
      "player": "David Fry (CLE)",
      "over_0.5_H": 40.0,
      "over_1.5_H": 10.0,
      "over_0.5_K": 80.0,
      "over_1.5_K": 10.0,
      "over_1.5_HRR": 30.0,
      "games_considered": 10,
      "player_id": 681807
    },
    {
      "player": "Rhys Hoskins (CLE)",
      "over_0.5_H": 40.0,
      "over_1.5_H": 10.0,
      "over_0.5_K": 80.0,
      "over_1.5_K": 10.0,
      "over_1.5_HRR": 30.0,
      "games_considered": 10,
      "player_id": 656555
    },
    {
      "player": "Cam Smith (HOU)",
      "over_0.5_H": 10.0,
      "over_1.5_H": 10.0,
      "over_0.5_K": 80.0,
      "over_1.5_K": 40.0,
      "over_1.5_HRR": 20.0,
      "games_considered": 10,
      "player_id": 701358
    },
    {
      "player": "Christian Walker (HOU)",
      "over_0.5_H": 50.0,
      "over_1.5_H": 30.0,
      "over_0.5_K": 80.0,
      "over_1.5_K": 30.0,
      "over_1.5_HRR": 40.0,
      "games_considered": 10,
      "player_id": 572233
    },
    {
      "player": "Gunnar Henderson (BAL)",
      "over_0.5_H": 40.0,
      "over_1.5_H": 30.0,
      "over_0.5_K": 90.0,
      "over_1.5_K": 50.0,
      "over_1.5_HRR": 40.0,
      "games_considered": 10,
      "player_id": 683002
    },
    {
      "player": "Weston Wilson (BAL)",
      "over_0.5_H": 60.0,
      "over_1.5_H": 0.0,
      "over_0.5_K": 80.0,
      "over_1.5_K": 20.0,
      "over_1.5_HRR": 60.0,
      "games_considered": 5,
      "player_id": 642215
    },
    {
      "player": "Ezequiel Tovar (COL)",
      "over_0.5_H": 30.0,
      "over_1.5_H": 10.0,
      "over_0.5_K": 80.0,
      "over_1.5_K": 40.0,
      "over_1.5_HRR": 20.0,
      "games_considered": 10,
      "player_id": 678662
    },
    {
      "player": "Hunter Goodman (COL)",
      "over_0.5_H": 80.0,
      "over_1.5_H": 30.0,
      "over_0.5_K": 100.0,
      "over_1.5_K": 50.0,
      "over_1.5_HRR": 70.0,
      "games_considered": 10,
      "player_id": 696100
    },
    {
      "player": "Mickey Moniak (COL)",
      "over_0.5_H": 100.0,
      "over_1.5_H": 30.0,
      "over_0.5_K": 80.0,
      "over_1.5_K": 10.0,
      "over_1.5_HRR": 50.0,
      "games_considered": 10,
      "player_id": 666160
    },
    {
      "player": "Rece Hinds (CIN)",
      "over_0.5_H": 50.0,
      "over_1.5_H": 0.0,
      "over_0.5_K": 87.5,
      "over_1.5_K": 62.5,
      "over_1.5_HRR": 37.5,
      "games_considered": 8,
      "player_id": 677956
    },
    {
      "player": "Tyler Stephenson (CIN)",
      "over_0.5_H": 40.0,
      "over_1.5_H": 0.0,
      "over_0.5_K": 80.0,
      "over_1.5_K": 50.0,
      "over_1.5_HRR": 20.0,
      "games_considered": 10,
      "player_id": 663886
    },
    {
      "player": "Jordan Walker (STL)",
      "over_0.5_H": 70.0,
      "over_1.5_H": 0.0,
      "over_0.5_K": 90.0,
      "over_1.5_K": 90.0,
      "over_1.5_HRR": 40.0,
      "games_considered": 10,
      "player_id": 691023
    },
    {
      "player": "Brandon Lowe (PIT)",
      "over_0.5_H": 60.0,
      "over_1.5_H": 20.0,
      "over_0.5_K": 90.0,
      "over_1.5_K": 40.0,
      "over_1.5_HRR": 50.0,
      "games_considered": 10,
      "player_id": 664040
    },
    {
      "player": "Bryan Reynolds (PIT)",
      "over_0.5_H": 30.0,
      "over_1.5_H": 20.0,
      "over_0.5_K": 80.0,
      "over_1.5_K": 50.0,
      "over_1.5_HRR": 30.0,
      "games_considered": 10,
      "player_id": 668804
    },
    {
      "player": "Oneil Cruz (PIT)",
      "over_0.5_H": 60.0,
      "over_1.5_H": 10.0,
      "over_0.5_K": 100.0,
      "over_1.5_K": 60.0,
      "over_1.5_HRR": 50.0,
      "games_considered": 10,
      "player_id": 665833
    },
    {
      "player": "Rafael Devers (SF)",
      "over_0.5_H": 60.0,
      "over_1.5_H": 20.0,
      "over_0.5_K": 80.0,
      "over_1.5_K": 50.0,
      "over_1.5_HRR": 60.0,
      "games_considered": 10,
      "player_id": 646240
    },
    {
      "player": "Willy Adames (SF)",
      "over_0.5_H": 40.0,
      "over_1.5_H": 10.0,
      "over_0.5_K": 90.0,
      "over_1.5_K": 80.0,
      "over_1.5_HRR": 30.0,
      "games_considered": 10,
      "player_id": 642715
    },
    {
      "player": "Jarren Duran (BOS)",
      "over_0.5_H": 50.0,
      "over_1.5_H": 10.0,
      "over_0.5_K": 80.0,
      "over_1.5_K": 10.0,
      "over_1.5_HRR": 30.0,
      "games_considered": 10,
      "player_id": 680776
    },
    {
      "player": "Roman Anthony (BOS)",
      "over_0.5_H": 60.0,
      "over_1.5_H": 20.0,
      "over_0.5_K": 90.0,
      "over_1.5_K": 20.0,
      "over_1.5_HRR": 50.0,
      "games_considered": 10,
      "player_id": 701350
    },
    {
      "player": "Willson Contreras (BOS)",
      "over_0.5_H": 70.0,
      "over_1.5_H": 10.0,
      "over_0.5_K": 90.0,
      "over_1.5_K": 30.0,
      "over_1.5_HRR": 40.0,
      "games_considered": 10,
      "player_id": 575929
    },
    {
      "player": "Kazuma Okamoto (TOR)",
      "over_0.5_H": 50.0,
      "over_1.5_H": 40.0,
      "over_0.5_K": 90.0,
      "over_1.5_K": 20.0,
      "over_1.5_HRR": 50.0,
      "games_considered": 10,
      "player_id": 672960
    },
    {
      "player": "Tyler Heineman (TOR)",
      "over_0.5_H": 30.0,
      "over_1.5_H": 0.0,
      "over_0.5_K": 80.0,
      "over_1.5_K": 10.0,
      "over_1.5_HRR": 10.0,
      "games_considered": 10,
      "player_id": 623168
    },
    {
      "player": "Brady House (WSH)",
      "over_0.5_H": 80.0,
      "over_1.5_H": 0.0,
      "over_0.5_K": 100.0,
      "over_1.5_K": 40.0,
      "over_1.5_HRR": 50.0,
      "games_considered": 10,
      "player_id": 691781
    },
    {
      "player": "CJ Abrams (WSH)",
      "over_0.5_H": 30.0,
      "over_1.5_H": 0.0,
      "over_0.5_K": 80.0,
      "over_1.5_K": 20.0,
      "over_1.5_HRR": 20.0,
      "games_considered": 10,
      "player_id": 682928
    },
    {
      "player": "James Wood (WSH)",
      "over_0.5_H": 60.0,
      "over_1.5_H": 10.0,
      "over_0.5_K": 90.0,
      "over_1.5_K": 50.0,
      "over_1.5_HRR": 50.0,
      "games_considered": 10,
      "player_id": 695578
    },
    {
      "player": "MJ Melendez (NYM)",
      "over_0.5_H": 50.0,
      "over_1.5_H": 25.0,
      "over_0.5_K": 87.5,
      "over_1.5_K": 37.5,
      "over_1.5_HRR": 37.5,
      "games_considered": 8,
      "player_id": 669004
    },
    {
      "player": "Marcus Semien (NYM)",
      "over_0.5_H": 70.0,
      "over_1.5_H": 30.0,
      "over_0.5_K": 80.0,
      "over_1.5_K": 10.0,
      "over_1.5_HRR": 40.0,
      "games_considered": 10,
      "player_id": 543760
    },
    {
      "player": "Kerry Carpenter (DET)",
      "over_0.5_H": 60.0,
      "over_1.5_H": 20.0,
      "over_0.5_K": 80.0,
      "over_1.5_K": 10.0,
      "over_1.5_HRR": 40.0,
      "games_considered": 10,
      "player_id": 681481
    },
    {
      "player": "Cal Raleigh (SEA)",
      "over_0.5_H": 70.0,
      "over_1.5_H": 30.0,
      "over_0.5_K": 80.0,
      "over_1.5_K": 10.0,
      "over_1.5_HRR": 60.0,
      "games_considered": 10,
      "player_id": 663728
    },
    {
      "player": "Connor Joe (SEA)",
      "over_0.5_H": 60.0,
      "over_1.5_H": 0.0,
      "over_0.5_K": 80.0,
      "over_1.5_K": 20.0,
      "over_1.5_HRR": 40.0,
      "games_considered": 5,
      "player_id": 656582
    },
    {
      "player": "Byron Buxton (MIN)",
      "over_0.5_H": 80.0,
      "over_1.5_H": 10.0,
      "over_0.5_K": 90.0,
      "over_1.5_K": 50.0,
      "over_1.5_HRR": 50.0,
      "games_considered": 10,
      "player_id": 621439
    },
    {
      "player": "Kody Clemens (MIN)",
      "over_0.5_H": 70.0,
      "over_1.5_H": 10.0,
      "over_0.5_K": 90.0,
      "over_1.5_K": 0.0,
      "over_1.5_HRR": 20.0,
      "games_considered": 10,
      "player_id": 665019
    },
    {
      "player": "Matt Wallner (MIN)",
      "over_0.5_H": 30.0,
      "over_1.5_H": 0.0,
      "over_0.5_K": 80.0,
      "over_1.5_K": 10.0,
      "over_1.5_HRR": 10.0,
      "games_considered": 10,
      "player_id": 670242
    },
    {
      "player": "Royce Lewis (MIN)",
      "over_0.5_H": 60.0,
      "over_1.5_H": 10.0,
      "over_0.5_K": 80.0,
      "over_1.5_K": 30.0,
      "over_1.5_HRR": 40.0,
      "games_considered": 10,
      "player_id": 668904
    },
    {
      "player": "Tristan Gray (MIN)",
      "over_0.5_H": 70.0,
      "over_1.5_H": 20.0,
      "over_0.5_K": 80.0,
      "over_1.5_K": 40.0,
      "over_1.5_HRR": 50.0,
      "games_considered": 10,
      "player_id": 656484
    },
    {
      "player": "Jo Adell (LAA)",
      "over_0.5_H": 70.0,
      "over_1.5_H": 0.0,
      "over_0.5_K": 80.0,
      "over_1.5_K": 30.0,
      "over_1.5_HRR": 50.0,
      "games_considered": 10,
      "player_id": 666176
    },
    {
      "player": "Jorge Soler (LAA)",
      "over_0.5_H": 80.0,
      "over_1.5_H": 20.0,
      "over_0.5_K": 80.0,
      "over_1.5_K": 40.0,
      "over_1.5_HRR": 50.0,
      "games_considered": 10,
      "player_id": 624585
    },
    {
      "player": "Zach Neto (LAA)",
      "over_0.5_H": 70.0,
      "over_1.5_H": 20.0,
      "over_0.5_K": 100.0,
      "over_1.5_K": 30.0,
      "over_1.5_HRR": 50.0,
      "games_considered": 10,
      "player_id": 687263
    },
    {
      "player": "Andrew Benintendi (CWS)",
      "over_0.5_H": 60.0,
      "over_1.5_H": 30.0,
      "over_0.5_K": 90.0,
      "over_1.5_K": 20.0,
      "over_1.5_HRR": 60.0,
      "games_considered": 10,
      "player_id": 643217
    },
    {
      "player": "Colson Montgomery (CWS)",
      "over_0.5_H": 80.0,
      "over_1.5_H": 30.0,
      "over_0.5_K": 80.0,
      "over_1.5_K": 40.0,
      "over_1.5_HRR": 80.0,
      "games_considered": 10,
      "player_id": 695657
    },
    {
      "player": "Everson Pereira (CWS)",
      "over_0.5_H": 60.0,
      "over_1.5_H": 30.0,
      "over_0.5_K": 80.0,
      "over_1.5_K": 30.0,
      "over_1.5_HRR": 50.0,
      "games_considered": 10,
      "player_id": 677592
    },
    {
      "player": "Munetaka Murakami (CWS)",
      "over_0.5_H": 80.0,
      "over_1.5_H": 40.0,
      "over_0.5_K": 80.0,
      "over_1.5_K": 50.0,
      "over_1.5_HRR": 70.0,
      "games_considered": 10,
      "player_id": 808959
    },
    {
      "player": "Brandon Lockridge (MIL)",
      "over_0.5_H": 80.0,
      "over_1.5_H": 10.0,
      "over_0.5_K": 80.0,
      "over_1.5_K": 40.0,
      "over_1.5_HRR": 40.0,
      "games_considered": 10,
      "player_id": 663604
    },
    {
      "player": "Brice Turang (MIL)",
      "over_0.5_H": 50.0,
      "over_1.5_H": 20.0,
      "over_0.5_K": 80.0,
      "over_1.5_K": 50.0,
      "over_1.5_HRR": 30.0,
      "games_considered": 10,
      "player_id": 668930
    },
    {
      "player": "Garrett Mitchell (MIL)",
      "over_0.5_H": 30.0,
      "over_1.5_H": 20.0,
      "over_0.5_K": 80.0,
      "over_1.5_K": 40.0,
      "over_1.5_HRR": 40.0,
      "games_considered": 10,
      "player_id": 669003
    },
    {
      "player": "Jake Bauers (MIL)",
      "over_0.5_H": 60.0,
      "over_1.5_H": 40.0,
      "over_0.5_K": 80.0,
      "over_1.5_K": 10.0,
      "over_1.5_HRR": 50.0,
      "games_considered": 10,
      "player_id": 641343
    },
    {
      "player": "Jazz Chisholm Jr. (NYY)",
      "over_0.5_H": 50.0,
      "over_1.5_H": 40.0,
      "over_0.5_K": 80.0,
      "over_1.5_K": 20.0,
      "over_1.5_HRR": 50.0,
      "games_considered": 10,
      "player_id": 665862
    },
    {
      "player": "Evan Carter (TEX)",
      "over_0.5_H": 60.0,
      "over_1.5_H": 10.0,
      "over_0.5_K": 80.0,
      "over_1.5_K": 20.0,
      "over_1.5_HRR": 30.0,
      "games_considered": 10,
      "player_id": 694497
    },
    {
      "player": "Jake Burger (TEX)",
      "over_0.5_H": 50.0,
      "over_1.5_H": 10.0,
      "over_0.5_K": 80.0,
      "over_1.5_K": 40.0,
      "over_1.5_HRR": 30.0,
      "games_considered": 10,
      "player_id": 669394
    },
    {
      "player": "Kyle Higashioka (TEX)",
      "over_0.5_H": 50.0,
      "over_1.5_H": 20.0,
      "over_0.5_K": 80.0,
      "over_1.5_K": 30.0,
      "over_1.5_HRR": 20.0,
      "games_considered": 10,
      "player_id": 543309
    },
    {
      "player": "Isaac Collins (KC)",
      "over_0.5_H": 60.0,
      "over_1.5_H": 40.0,
      "over_0.5_K": 80.0,
      "over_1.5_K": 30.0,
      "over_1.5_HRR": 50.0,
      "games_considered": 10,
      "player_id": 686555
    },
    {
      "player": "Maikel Garcia (KC)",
      "over_0.5_H": 50.0,
      "over_1.5_H": 10.0,
      "over_0.5_K": 90.0,
      "over_1.5_K": 10.0,
      "over_1.5_HRR": 30.0,
      "games_considered": 10,
      "player_id": 672580
    },
    {
      "player": "Salvador Perez (KC)",
      "over_0.5_H": 50.0,
      "over_1.5_H": 30.0,
      "over_0.5_K": 80.0,
      "over_1.5_K": 50.0,
      "over_1.5_HRR": 40.0,
      "games_considered": 10,
      "player_id": 521692
    },
    {
      "player": "Max Muncy (ATH)",
      "over_0.5_H": 20.0,
      "over_1.5_H": 10.0,
      "over_0.5_K": 80.0,
      "over_1.5_K": 60.0,
      "over_1.5_HRR": 20.0,
      "games_considered": 10,
      "player_id": 691777
    },
    {
      "player": "Dansby Swanson (CHC)",
      "over_0.5_H": 40.0,
      "over_1.5_H": 30.0,
      "over_0.5_K": 80.0,
      "over_1.5_K": 10.0,
      "over_1.5_HRR": 40.0,
      "games_considered": 10,
      "player_id": 621020
    },
    {
      "player": "Michael Busch (CHC)",
      "over_0.5_H": 80.0,
      "over_1.5_H": 30.0,
      "over_0.5_K": 90.0,
      "over_1.5_K": 30.0,
      "over_1.5_HRR": 60.0,
      "games_considered": 10,
      "player_id": 683737
    },
    {
      "player": "Fernando Tatis Jr. (SD)",
      "over_0.5_H": 80.0,
      "over_1.5_H": 30.0,
      "over_0.5_K": 80.0,
      "over_1.5_K": 30.0,
      "over_1.5_HRR": 60.0,
      "games_considered": 10,
      "player_id": 665487
    },
    {
      "player": "Jackson Merrill (SD)",
      "over_0.5_H": 40.0,
      "over_1.5_H": 10.0,
      "over_0.5_K": 80.0,
      "over_1.5_K": 60.0,
      "over_1.5_HRR": 30.0,
      "games_considered": 10,
      "player_id": 701538
    },
    {
      "player": "Manny Machado (SD)",
      "over_0.5_H": 70.0,
      "over_1.5_H": 40.0,
      "over_0.5_K": 80.0,
      "over_1.5_K": 10.0,
      "over_1.5_HRR": 50.0,
      "games_considered": 10,
      "player_id": 592518
    },
    {
      "player": "Ramón Laureano (SD)",
      "over_0.5_H": 60.0,
      "over_1.5_H": 20.0,
      "over_0.5_K": 100.0,
      "over_1.5_K": 60.0,
      "over_1.5_HRR": 50.0,
      "games_considered": 10,
      "player_id": 657656
    },
    {
      "player": "Owen Caissie (MIA)",
      "over_0.5_H": 50.0,
      "over_1.5_H": 0.0,
      "over_0.5_K": 90.0,
      "over_1.5_K": 50.0,
      "over_1.5_HRR": 40.0,
      "games_considered": 10,
      "player_id": 683357
    },
    {
      "player": "Teoscar Hernández (LAD)",
      "over_0.5_H": 40.0,
      "over_1.5_H": 10.0,
      "over_0.5_K": 80.0,
      "over_1.5_K": 30.0,
      "over_1.5_HRR": 40.0,
      "games_considered": 10,
      "player_id": 606192
    }
  ],
  "hrr_qualifiers": [
    {
      "player": "Brayan Rocchio (CLE)",
      "over_0.5_H": 80.0,
      "over_1.5_H": 30.0,
      "over_0.5_K": 30.0,
      "over_1.5_K": 0.0,
      "over_1.5_HRR": 80.0,
      "games_considered": 10,
      "player_id": 677587
    },
    {
      "player": "Yordan Alvarez (HOU)",
      "over_0.5_H": 100.0,
      "over_1.5_H": 60.0,
      "over_0.5_K": 20.0,
      "over_1.5_K": 0.0,
      "over_1.5_HRR": 80.0,
      "games_considered": 10,
      "player_id": 670541
    },
    {
      "player": "Masyn Winn (STL)",
      "over_0.5_H": 80.0,
      "over_1.5_H": 50.0,
      "over_0.5_K": 70.0,
      "over_1.5_K": 30.0,
      "over_1.5_HRR": 80.0,
      "games_considered": 10,
      "player_id": 691026
    },
    {
      "player": "Jung Hoo Lee (SF)",
      "over_0.5_H": 80.0,
      "over_1.5_H": 60.0,
      "over_0.5_K": 40.0,
      "over_1.5_K": 0.0,
      "over_1.5_HRR": 80.0,
      "games_considered": 10,
      "player_id": 808982
    },
    {
      "player": "Daylen Lile (WSH)",
      "over_0.5_H": 70.0,
      "over_1.5_H": 40.0,
      "over_0.5_K": 60.0,
      "over_1.5_K": 10.0,
      "over_1.5_HRR": 80.0,
      "games_considered": 10,
      "player_id": 695734
    },
    {
      "player": "Kevin McGonigle (DET)",
      "over_0.5_H": 100.0,
      "over_1.5_H": 40.0,
      "over_0.5_K": 50.0,
      "over_1.5_K": 0.0,
      "over_1.5_HRR": 90.0,
      "games_considered": 10,
      "player_id": 805808
    },
    {
      "player": "Drake Baldwin (ATL)",
      "over_0.5_H": 80.0,
      "over_1.5_H": 40.0,
      "over_0.5_K": 70.0,
      "over_1.5_K": 30.0,
      "over_1.5_HRR": 80.0,
      "games_considered": 10,
      "player_id": 686948
    },
    {
      "player": "Matt Olson (ATL)",
      "over_0.5_H": 80.0,
      "over_1.5_H": 30.0,
      "over_0.5_K": 50.0,
      "over_1.5_K": 20.0,
      "over_1.5_HRR": 90.0,
      "games_considered": 10,
      "player_id": 621566
    },
    {
      "player": "Michael Harris II (ATL)",
      "over_0.5_H": 80.0,
      "over_1.5_H": 50.0,
      "over_0.5_K": 10.0,
      "over_1.5_K": 10.0,
      "over_1.5_HRR": 80.0,
      "games_considered": 10,
      "player_id": 671739
    },
    {
      "player": "Colson Montgomery (CWS)",
      "over_0.5_H": 80.0,
      "over_1.5_H": 30.0,
      "over_0.5_K": 80.0,
      "over_1.5_K": 40.0,
      "over_1.5_HRR": 80.0,
      "games_considered": 10,
      "player_id": 695657
    },
    {
      "player": "Miguel Vargas (CWS)",
      "over_0.5_H": 80.0,
      "over_1.5_H": 30.0,
      "over_0.5_K": 50.0,
      "over_1.5_K": 10.0,
      "over_1.5_HRR": 80.0,
      "games_considered": 10,
      "player_id": 678246
    },
    {
      "player": "Jose Fernandez (AZ)",
      "over_0.5_H": 90.0,
      "over_1.5_H": 40.0,
      "over_0.5_K": 70.0,
      "over_1.5_K": 10.0,
      "over_1.5_HRR": 80.0,
      "games_considered": 10,
      "player_id": 699912
    },
    {
      "player": "Josh Jung (TEX)",
      "over_0.5_H": 90.0,
      "over_1.5_H": 40.0,
      "over_0.5_K": 40.0,
      "over_1.5_K": 10.0,
      "over_1.5_HRR": 80.0,
      "games_considered": 10,
      "player_id": 673962
    },
    {
      "player": "Shea Langeliers (ATH)",
      "over_0.5_H": 80.0,
      "over_1.5_H": 50.0,
      "over_0.5_K": 60.0,
      "over_1.5_K": 20.0,
      "over_1.5_HRR": 80.0,
      "games_considered": 10,
      "player_id": 669127
    }
  ],
  "parlay_suggestions": [
    {
      "game": "St. Louis Cardinals @ Pittsburgh Pirates",
      "avg_leg_hit_rate": 92.5,
      "legs": [
        {
          "player": "Oneil Cruz (PIT)",
          "prop": "Over 0.5 Strikeouts",
          "hit_rate": 100.0,
          "games_considered": 10
        },
        {
          "player": "Iván Herrera (STL)",
          "prop": "Over 0.5 Hits",
          "hit_rate": 90.0,
          "games_considered": 10
        },
        {
          "player": "Jordan Walker (STL)",
          "prop": "Over 1.5 Strikeouts",
          "hit_rate": 90.0,
          "games_considered": 10
        },
        {
          "player": "Brandon Lowe (PIT)",
          "prop": "Over 0.5 Strikeouts",
          "hit_rate": 90.0,
          "games_considered": 10
        }
      ]
    },
    {
      "game": "Detroit Tigers @ Atlanta Braves",
      "avg_leg_hit_rate": 92.5,
      "legs": [
        {
          "player": "Kevin McGonigle (DET)",
          "prop": "Over 0.5 Hits",
          "hit_rate": 100.0,
          "games_considered": 10
        },
        {
          "player": "Dominic Smith (ATL)",
          "prop": "Over 0.5 Hits",
          "hit_rate": 90.0,
          "games_considered": 10
        },
        {
          "player": "Ozzie Albies (ATL)",
          "prop": "Over 0.5 Hits",
          "hit_rate": 90.0,
          "games_considered": 10
        },
        {
          "player": "Matt Olson (ATL)",
          "prop": "Over 1.5 H+R+RBI",
          "hit_rate": 90.0,
          "games_considered": 10
        }
      ]
    },
    {
      "game": "Colorado Rockies @ Cincinnati Reds",
      "avg_leg_hit_rate": 91.9,
      "legs": [
        {
          "player": "Mickey Moniak (COL)",
          "prop": "Over 0.5 Hits",
          "hit_rate": 100.0,
          "games_considered": 10
        },
        {
          "player": "Hunter Goodman (COL)",
          "prop": "Over 0.5 Strikeouts",
          "hit_rate": 100.0,
          "games_considered": 10
        },
        {
          "player": "Rece Hinds (CIN)",
          "prop": "Over 0.5 Strikeouts",
          "hit_rate": 87.5,
          "games_considered": 8
        },
        {
          "player": "Troy Johnston (COL)",
          "prop": "Over 0.5 Hits",
          "hit_rate": 80.0,
          "games_considered": 10
        }
      ]
    },
    {
      "game": "Boston Red Sox @ Toronto Blue Jays",
      "avg_leg_hit_rate": 90.0,
      "legs": [
        {
          "player": "Ernie Clement (TOR)",
          "prop": "Over 0.5 Hits",
          "hit_rate": 90.0,
          "games_considered": 10
        },
        {
          "player": "Roman Anthony (BOS)",
          "prop": "Over 0.5 Strikeouts",
          "hit_rate": 90.0,
          "games_considered": 10
        },
        {
          "player": "Willson Contreras (BOS)",
          "prop": "Over 0.5 Strikeouts",
          "hit_rate": 90.0,
          "games_considered": 10
        },
        {
          "player": "Kazuma Okamoto (TOR)",
          "prop": "Over 0.5 Strikeouts",
          "hit_rate": 90.0,
          "games_considered": 10
        }
      ]
    },
    {
      "game": "Los Angeles Angels @ Chicago White Sox",
      "avg_leg_hit_rate": 90.0,
      "legs": [
        {
          "player": "Zach Neto (LAA)",
          "prop": "Over 0.5 Strikeouts",
          "hit_rate": 100.0,
          "games_considered": 10
        },
        {
          "player": "Chase Meidroth (CWS)",
          "prop": "Over 0.5 Hits",
          "hit_rate": 90.0,
          "games_considered": 10
        },
        {
          "player": "Andrew Benintendi (CWS)",
          "prop": "Over 0.5 Strikeouts",
          "hit_rate": 90.0,
          "games_considered": 10
        },
        {
          "player": "Jorge Soler (LAA)",
          "prop": "Over 0.5 Hits",
          "hit_rate": 80.0,
          "games_considered": 10
        }
      ]
    },
    {
      "game": "Arizona Diamondbacks @ Milwaukee Brewers",
      "avg_leg_hit_rate": 90.0,
      "legs": [
        {
          "player": "Ildemaro Vargas (AZ)",
          "prop": "Over 0.5 Hits",
          "hit_rate": 100.0,
          "games_considered": 10
        },
        {
          "player": "Jose Fernandez (AZ)",
          "prop": "Over 0.5 Hits",
          "hit_rate": 90.0,
          "games_considered": 10
        },
        {
          "player": "Ketel Marte (AZ)",
          "prop": "Over 0.5 Hits",
          "hit_rate": 90.0,
          "games_considered": 10
        },
        {
          "player": "Alek Thomas (AZ)",
          "prop": "Over 0.5 Hits",
          "hit_rate": 80.0,
          "games_considered": 10
        }
      ]
    },
    {
      "game": "Washington Nationals @ New York Mets",
      "avg_leg_hit_rate": 89.4,
      "legs": [
        {
          "player": "Brady House (WSH)",
          "prop": "Over 0.5 Strikeouts",
          "hit_rate": 100.0,
          "games_considered": 10
        },
        {
          "player": "James Wood (WSH)",
          "prop": "Over 0.5 Strikeouts",
          "hit_rate": 90.0,
          "games_considered": 10
        },
        {
          "player": "MJ Melendez (NYM)",
          "prop": "Over 0.5 Strikeouts",
          "hit_rate": 87.5,
          "games_considered": 8
        },
        {
          "player": "Bo Bichette (NYM)",
          "prop": "Over 0.5 Hits",
          "hit_rate": 80.0,
          "games_considered": 10
        }
      ]
    },
    {
      "game": "Houston Astros @ Baltimore Orioles",
      "avg_leg_hit_rate": 87.5,
      "legs": [
        {
          "player": "Yordan Alvarez (HOU)",
          "prop": "Over 0.5 Hits",
          "hit_rate": 100.0,
          "games_considered": 10
        },
        {
          "player": "Gunnar Henderson (BAL)",
          "prop": "Over 0.5 Strikeouts",
          "hit_rate": 90.0,
          "games_considered": 10
        },
        {
          "player": "Cam Smith (HOU)",
          "prop": "Over 0.5 Strikeouts",
          "hit_rate": 80.0,
          "games_considered": 10
        },
        {
          "player": "Christian Walker (HOU)",
          "prop": "Over 0.5 Strikeouts",
          "hit_rate": 80.0,
          "games_considered": 10
        }
      ]
    },
    {
      "game": "Kansas City Royals @ Athletics",
      "avg_leg_hit_rate": 87.5,
      "legs": [
        {
          "player": "Bobby Witt Jr. (KC)",
          "prop": "Over 0.5 Hits",
          "hit_rate": 90.0,
          "games_considered": 10
        },
        {
          "player": "Jac Caglianone (KC)",
          "prop": "Over 0.5 Hits",
          "hit_rate": 90.0,
          "games_considered": 10
        },
        {
          "player": "Maikel Garcia (KC)",
          "prop": "Over 0.5 Strikeouts",
          "hit_rate": 90.0,
          "games_considered": 10
        },
        {
          "player": "Carlos Cortes (ATH)",
          "prop": "Over 0.5 Hits",
          "hit_rate": 80.0,
          "games_considered": 10
        }
      ]
    },
    {
      "game": "Chicago Cubs @ San Diego Padres",
      "avg_leg_hit_rate": 87.5,
      "legs": [
        {
          "player": "Ramón Laureano (SD)",
          "prop": "Over 0.5 Strikeouts",
          "hit_rate": 100.0,
          "games_considered": 10
        },
        {
          "player": "Michael Busch (CHC)",
          "prop": "Over 0.5 Strikeouts",
          "hit_rate": 90.0,
          "games_considered": 10
        },
        {
          "player": "Carson Kelly (CHC)",
          "prop": "Over 0.5 Hits",
          "hit_rate": 80.0,
          "games_considered": 10
        },
        {
          "player": "Ian Happ (CHC)",
          "prop": "Over 0.5 Hits",
          "hit_rate": 80.0,
          "games_considered": 10
        }
      ]
    },
    {
      "game": "Tampa Bay Rays @ Cleveland Guardians",
      "avg_leg_hit_rate": 85.0,
      "legs": [
        {
          "player": "Junior Caminero (TB)",
          "prop": "Over 0.5 Hits",
          "hit_rate": 90.0,
          "games_considered": 10
        },
        {
          "player": "Jonathan Aranda (TB)",
          "prop": "Over 0.5 Strikeouts",
          "hit_rate": 90.0,
          "games_considered": 10
        },
        {
          "player": "Jake Fraley (TB)",
          "prop": "Over 0.5 Hits",
          "hit_rate": 80.0,
          "games_considered": 10
        },
        {
          "player": "Brayan Rocchio (CLE)",
          "prop": "Over 0.5 Hits",
          "hit_rate": 80.0,
          "games_considered": 10
        }
      ]
    },
    {
      "game": "Seattle Mariners @ Minnesota Twins",
      "avg_leg_hit_rate": 85.0,
      "legs": [
        {
          "player": "Byron Buxton (MIN)",
          "prop": "Over 0.5 Strikeouts",
          "hit_rate": 90.0,
          "games_considered": 10
        },
        {
          "player": "Kody Clemens (MIN)",
          "prop": "Over 0.5 Strikeouts",
          "hit_rate": 90.0,
          "games_considered": 10
        },
        {
          "player": "Cole Young (SEA)",
          "prop": "Over 0.5 Hits",
          "hit_rate": 80.0,
          "games_considered": 10
        },
        {
          "player": "Julio Rodríguez (SEA)",
          "prop": "Over 0.5 Hits",
          "hit_rate": 80.0,
          "games_considered": 10
        }
      ]
    },
    {
      "game": "San Francisco Giants @ Philadelphia Phillies",
      "avg_leg_hit_rate": 82.5,
      "legs": [
        {
          "player": "Willy Adames (SF)",
          "prop": "Over 0.5 Strikeouts",
          "hit_rate": 90.0,
          "games_considered": 10
        },
        {
          "player": "Jung Hoo Lee (SF)",
          "prop": "Over 0.5 Hits",
          "hit_rate": 80.0,
          "games_considered": 10
        },
        {
          "player": "Bryson Stott (PHI)",
          "prop": "Over 0.5 Hits",
          "hit_rate": 80.0,
          "games_considered": 10
        },
        {
          "player": "Rafael Devers (SF)",
          "prop": "Over 0.5 Strikeouts",
          "hit_rate": 80.0,
          "games_considered": 10
        }
      ]
    },
    {
      "game": "New York Yankees @ Texas Rangers",
      "avg_leg_hit_rate": 82.5,
      "legs": [
        {
          "player": "Josh Jung (TEX)",
          "prop": "Over 0.5 Hits",
          "hit_rate": 90.0,
          "games_considered": 10
        },
        {
          "player": "José Caballero (NYY)",
          "prop": "Over 0.5 Hits",
          "hit_rate": 80.0,
          "games_considered": 10
        },
        {
          "player": "Jazz Chisholm Jr. (NYY)",
          "prop": "Over 0.5 Strikeouts",
          "hit_rate": 80.0,
          "games_considered": 10
        },
        {
          "player": "Evan Carter (TEX)",
          "prop": "Over 0.5 Strikeouts",
          "hit_rate": 80.0,
          "games_considered": 10
        }
      ]
    },
    {
      "game": "Miami Marlins @ Los Angeles Dodgers",
      "avg_leg_hit_rate": 82.5,
      "legs": [
        {
          "player": "Owen Caissie (MIA)",
          "prop": "Over 0.5 Strikeouts",
          "hit_rate": 90.0,
          "games_considered": 10
        },
        {
          "player": "Liam Hicks (MIA)",
          "prop": "Over 0.5 Hits",
          "hit_rate": 80.0,
          "games_considered": 10
        },
        {
          "player": "Otto Lopez (MIA)",
          "prop": "Over 0.5 Hits",
          "hit_rate": 80.0,
          "games_considered": 10
        },
        {
          "player": "Max Muncy (LAD)",
          "prop": "Over 0.5 Hits",
          "hit_rate": 80.0,
          "games_considered": 10
        }
      ]
    }
  ]
}